Metadata-Version: 2.1
Name: odoo-addon-mrp_multi_level
Version: 18.0.1.3.2
Requires-Python: >=3.10
Requires-Dist: odoo-addon-mrp_warehouse_calendar==18.0.*
Requires-Dist: odoo==18.0.*
Summary: Adds an MRP Scheduler
Home-page: https://github.com/OCA/manufacture
License: LGPL-3
Author: Ucamco, ForgeFlow, Odoo Community Association (OCA)
Author-email: support@odoo-community.org
Classifier: Programming Language :: Python
Classifier: Framework :: Odoo
Classifier: Framework :: Odoo :: 18.0
Classifier: License :: OSI Approved :: GNU Lesser General Public License v3 (LGPLv3)
Classifier: Development Status :: 5 - Production/Stable
